my_regression_model/__init__.py
my_regression_model/my_regression_model.py
my_regression_model812-1.0.0.dist-info/LICENSE.txt
my_regression_model812-1.0.0.dist-info/METADATA
my_regression_model812-1.0.0.dist-info/WHEEL
my_regression_model812-1.0.0.dist-info/top_level.txt
my_regression_model812-1.0.0.dist-info/RECORD
